{
  "title": "IMG_6876.JPG",
  "description": "",
  "imageViews": "0",
  "creationTime": {
    "timestamp": "1766494245",
    "formatted": "23 de dez. de 2025, 12:50:45 UTC"
  },
  "photoTakenTime": {
    "timestamp": "1407326890",
    "formatted": "6 de ago. de 2014, 12:08:10 UTC"
  },
  "geoData": {
    "latitude": 43.7678168,
    "longitude": 11.2550348,
    "altitude": 0.0,
    "latitudeSpan": 0.0,
    "longitudeSpan": 0.0
  },
  "url": "https://photos.google.com/photo/AF1QipO0OMe6Rati_u9_t7A74p47vtOKW8St-1BrCGFK",
  "googlePhotosOrigin": {
    "driveDesktopUploader": {
      "version": "BACKUP_AND_SYNC"
    }
  }
}